setup.cfg
setup.py
keyword_density.egg-info/PKG-INFO
keyword_density.egg-info/SOURCES.txt
keyword_density.egg-info/dependency_links.txt
keyword_density.egg-info/top_level.txt
kwdensity/__init__.py
kwdensity/density_calculator.py
kwdensity/tokenizer.py
kwdensity/filters/__init__.py
kwdensity/filters/base_filter.py
kwdensity/filters/greek_filter.py
kwdensity/filters/stopwords_filter.py
test/test_density_calculatory.py
test/test_tokenizer.py