Metadata-Version: 1.1
Name: keyword-density
Version: 0.1
Summary: Computes the keyword density of a string
Home-page: https://github.com/gosom/pykeyword_density
Author: Giorgos Komninos
Author-email: g@gkomninos.com
License: BSD
Download-URL: https://github.com/gosom/pykeyword_density/archive/0.1.tar.gz
Keywords: keyword density seo
Platform: UNKNOWN
